geosections/__init__.py
geosections/base.py
geosections/check.py
geosections/cli.py
geosections/plotting.py
geosections/read.py
geosections/utils.py
geosections-0.1.6.dist-info/METADATA
geosections-0.1.6.dist-info/WHEEL
geosections-0.1.6.dist-info/entry_points.txt
geosections-0.1.6.dist-info/licenses/LICENSE
geosections-0.1.6.dist-info/RECORD
