Metadata-Version: 2.4
Name: geosections
Version: 0.1.6
Summary: Simple command line tool to create geological cross-sections
Project-URL: Homepage, https://github.com/Deltares-research/geosections
Project-URL: Repository, https://github.com/Deltares-research/geosections
Project-URL: Issues, https://github.com/Deltares-research/geosections/issues
Author-email: smknaake <bas.knaake@deltares.nl>
License: MIT License
License-File: LICENSE
Keywords: CLI,Cross-sections,Deltares,Geology
Classifier: Development Status :: 2 - Pre-Alpha
Classifier: Intended Audience :: Science/Research
Classifier: License :: OSI Approved :: MIT License
Classifier: Operating System :: OS Independent
Classifier: Programming Language :: Python
Classifier: Topic :: Scientific/Engineering
Requires-Python: >=3.12
Requires-Dist: click<8.2
Requires-Dist: geopandas
Requires-Dist: geost
Requires-Dist: matplotlib
Requires-Dist: numpy
Requires-Dist: pandas
Requires-Dist: pillow
Requires-Dist: pydantic
Requires-Dist: rioxarray
Requires-Dist: shapely
Requires-Dist: typer
Requires-Dist: xarray
